legipy/__init__.py
legipy/__main__.py
legipy/cli.py
legipy/common.py
legipy/version.py
legipy/models/__init__.py
legipy/models/base.py
legipy/models/code.py
legipy/models/law.py
legipy/models/legislature.py
legipy/parsers/__init__.py
legipy/parsers/code_parser.py
legipy/parsers/common_law_list_parser.py
legipy/parsers/law_parser.py
legipy/parsers/legislature_list_parser.py
legipy/parsers/pending_law_list_parser.py
legipy/parsers/published_law_list_parser.py
legipy/services/__init__.py
legipy/services/code_service.py
legipy/services/law_service.py
legipy/services/legislature_service.py
tests/__init__.py
tests/test_code_service.py
tests/test_law_service.py
tests/test_legislature_service.py
legipy-0.1.2.dist-info/LICENSE
legipy-0.1.2.dist-info/METADATA
legipy-0.1.2.dist-info/WHEEL
legipy-0.1.2.dist-info/entry_points.txt
legipy-0.1.2.dist-info/top_level.txt
legipy-0.1.2.dist-info/RECORD
