Metadata-Version: 2.1
Name: legipy
Version: 0.1.2
Summary: Python client for legifrance.gouv.fr website
Home-page: https://github.com/regardscitoyens/legipy
Author: Regards Citoyens
Author-email: contact@regardscitoyens.org
License: MIT
Keywords: scraping politics data france
Platform: UNKNOWN
Classifier: Development Status :: 4 - Beta
Classifier: License :: OSI Approved :: MIT License
Classifier: Operating System :: OS Independent
Classifier: Programming Language :: Python :: 2
Classifier: Programming Language :: Python :: 2.7
Classifier: Programming Language :: Python :: 3
Classifier: Programming Language :: Python :: 3.4
Classifier: Programming Language :: Python :: 3.5
Classifier: Programming Language :: Python :: 3.6
Classifier: Programming Language :: Python :: 3.7
Classifier: Programming Language :: Python :: Implementation :: PyPy
Requires-Python: >=2.7, !=3.0.*, !=3.1.*, !=3.2.*
Requires-Dist: beautifulsoup4 (<4.7,>=4.6)
Requires-Dist: click (<6.8,>=6.7)
Requires-Dist: html5lib (<1.1,>=1.0)
Requires-Dist: requests (<2.21,>=2.20)
Requires-Dist: urllib3[secure] (<1.25,>=1.24)
Requires-Dist: six (<1.12,>=1.11)
Provides-Extra: test
Requires-Dist: coverage (<4.5,>=4.4) ; extra == 'test'
Requires-Dist: pytest (<3.5,>=3.4) ; extra == 'test'
Requires-Dist: pytest-cov (<2.6,>=2.5) ; extra == 'test'
Requires-Dist: vcrpy (<1.12,>=1.11) ; extra == 'test'
